websearchdict/__init__.py
websearchdict/dictionary/__init__.py
websearchdict/dictionary/entry.py
websearchdict/web/__init__.py
websearchdict/web/automation.py
websearchdict/web/constants.py
websearchdict/web/fetch.py
websearchdict/web/parser.py
websearchdict/web/structure.py
websearchdict-0.0.1.dist-info/METADATA
websearchdict-0.0.1.dist-info/WHEEL
websearchdict-0.0.1.dist-info/licenses/LICENSE
websearchdict-0.0.1.dist-info/RECORD
