Metadata-Version: 2.1
Name: websearchdict
Version: 0.0.1
Summary: A Dictionary API based on web searches (mainly just google search haha)
Project-URL: Homepage, https://github.com/nickumia/web-search-dictionary
Project-URL: Bug Tracker, https://github.com/nickumia/web-search-dictionary/issues
Author-email: nickumia <nickumia6@gmail.com>
License-File: LICENSE
Classifier: License :: OSI Approved :: MIT License
Classifier: Operating System :: OS Independent
Classifier: Programming Language :: Python :: 3
Requires-Python: >=3.7
Requires-Dist: lxml>=4.7.1
Requires-Dist: requests
Requires-Dist: selenium
